{
  "pink floyd": "Rock",
  "陈奕迅": "Cantopop",
  "miles davis": "Jazz",
  "mozart": "Classical",
  "beethoven": "Classical",
  "mendelssohn": "Classical",
  "dvorak": "Classical",
  "alison krauss": "Folk",
  "eva cassidy": "Folk",
  "jane monheit": "Jazz",
  "karrin allyson": "Jazz",
  "stacey kent": "Jazz",
  "carol kidd": "Jazz",
  "nnenna freelon": "Jazz",
  "王菲": "Cantopop",
  "陈百强": "Cantopop",
  "billie eilish": "Pop",
  "eagles": "Rock",
  "keith jarrett": "Jazz",
  "mari nakamoto": "",
  "唐朝": "Metal",
  "adele": "Pop",
  "junkie xl": "Electronic",
  "carlo maria giulini": "Classical",
  "wiener philharmoniker": "Classical",
  "james levine": "Classical",
  "schubert": "Classical",
  "brahms": "Classical",
  "dvorák": "Classical",
  "bach": "Classical",
  "群星": "",
  "罗文": "Cantopop",
  "甄妮": "Cantopop",
  "megadeth": "Metal",
  "朴树": "",
  "山口百惠": "",
  "刘若英": "Classical",
  "cannonball adderley": "",
  "akina nakamori": "",
  "sally yeh": "",
  "art blakey, the jazz messengers": "",
  "g.e.m.邓紫棋": "",
  "张国荣": "Cantopop",
  "beyond": "Cantopop",
  "faye wong": "",
  "myrath": "Metal",
  "pathfinder": "",
  "seraphiel": "",
  "unknown artist": "",
  "dsd64": "",
  "卢冠廷, 莫文蔚": "",
  "卢冠廷": "Cantopop",
  "marisa": "Pop",
  "sylvia hotel": "",
  "tish hinojosa": "Folk",
  "古典小提琴名盘《妈妈教我的歌》": "",
  "mozart, various": "",
  "【风之声】音箱测试cd-1号碟": "",
  "闲鱼@平头塞耳机": "",
  "左麟右李": "",
  "蔡琴": "",
  "various artists": "",
  "nightwish": "Metal",
  "姜育恒": "Mandopop",
  "李克勤": "Cantopop",
  "王杰": "Mandopop",
  "许巍": "Rock",
  "信乐团": "",
  "宋冬野": "",
  "邝美云": "Cantopop",
  "许巍.1997": "",
  "许茹芸": "Cantopop",
  "anthony wong": "",
  "carlo maria giulini, wiener philharmoniker": "",
  "陈慧娴": ""
}